rhosocial/activerecord/backend/impl/mysql/__init__.py
rhosocial/activerecord/backend/impl/mysql/backend.py
rhosocial/activerecord/backend/impl/mysql/config.py
rhosocial/activerecord/backend/impl/mysql/dialect.py
rhosocial/activerecord/backend/impl/mysql/transaction.py
rhosocial/activerecord/backend/impl/mysql/type_converters.py
rhosocial/activerecord/backend/impl/mysql/types.py
rhosocial_activerecord_mysql-1.0.0.dev3.dist-info/licenses/LICENSE
rhosocial_activerecord_mysql-1.0.0.dev3.dist-info/METADATA
rhosocial_activerecord_mysql-1.0.0.dev3.dist-info/WHEEL
rhosocial_activerecord_mysql-1.0.0.dev3.dist-info/top_level.txt
rhosocial_activerecord_mysql-1.0.0.dev3.dist-info/RECORD
