Metadata-Version: 2.4
Name: rhosocial_activerecord_mysql
Version: 1.0.0.dev3
Summary: MySQL backend implementation for rhosocial-activerecord, providing a robust and optimized MySQL database support.
Author-email: vistart <i@vistart.me>
License:                                  Apache License
Project-URL: Homepage, https://github.com/rhosocial/python-activerecord-mysql
Project-URL: Documentation, https://docs.python-activerecord.dev.rho.social
Project-URL: Repository, https://github.com/rhosocial/python-activerecord-mysql.git
Project-URL: Issues, https://github.com/rhosocial/python-activerecord-mysql/issues
Keywords: activerecord,orm,database,mysql,pymysql,mysql-connector
Classifier: Development Status :: 3 - Alpha
Classifier: Intended Audience :: Developers
Classifier: License :: OSI Approved :: Apache Software License
Classifier: Programming Language :: Python :: 3
Classifier: Programming Language :: Python :: 3.8
Classifier: Programming Language :: Python :: 3.9
Classifier: Programming Language :: Python :: 3.10
Classifier: Programming Language :: Python :: 3.11
Classifier: Programming Language :: Python :: 3.12
Classifier: Programming Language :: Python :: 3.13
Classifier: Programming Language :: Python :: 3.14
Classifier: Programming Language :: Python :: 3 :: Only
Classifier: Framework :: Pydantic
Classifier: Framework :: Pydantic :: 2
Classifier: Intended Audience :: Developers
Classifier: Topic :: Database
Classifier: Topic :: Database :: Front-Ends
Classifier: Topic :: Software Development :: Libraries
Classifier: Topic :: Software Development :: Libraries :: Python Modules
Requires-Python: >=3.8
License-File: LICENSE
Requires-Dist: rhosocial-activerecord<2.0.0,>=0.9.0
Requires-Dist: mysql-connector-python>=9.0.0
Provides-Extra: test
Requires-Dist: pytest>=7.0.0; extra == "test"
Requires-Dist: coverage>=7.0.0; extra == "test"
Requires-Dist: pytest-asyncio>=0.10.0; extra == "test"
Requires-Dist: pytest-cov>=4.0.0; extra == "test"
Requires-Dist: rhosocial-activerecord[test]<2.0.0,>=0.9.0; extra == "test"
Requires-Dist: rhosocial-activerecord-testsuite; extra == "test"
Requires-Dist: tomli; python_version < "3.11" and extra == "test"
Provides-Extra: dev
Requires-Dist: black>=23.0.0; extra == "dev"
Requires-Dist: isort>=5.0.0; extra == "dev"
Requires-Dist: mypy>=1.0.0; extra == "dev"
Requires-Dist: ruff>=0.1.0; extra == "dev"
Requires-Dist: pre-commit>=3.0.0; extra == "dev"
Requires-Dist: rhosocial-activerecord-testsuite; extra == "dev"
Requires-Dist: tomli; python_version < "3.11" and extra == "dev"
Provides-Extra: docs
Requires-Dist: sphinx>=7.0.0; extra == "docs"
Requires-Dist: sphinx-rtd-theme>=1.0.0; extra == "docs"
Requires-Dist: myst-parser>=2.0.0; extra == "docs"
Dynamic: license-file
